[
  {
    "id": 1,
    "employeeId": "emp-001",
    "date": "2025-05-01",
    "startTime": "08:00:00",
    "endTime": "17:00:00",
    "breakStart": "12:00:00",
    "breakEnd": "13:00:00",
    "status": "scheduled"
  },
  {
    "id": 2,
    "employeeId": "emp-001",
    "date": "2025-05-02",
    "startTime": "08:00:00",
    "endTime": "17:00:00",
    "breakStart": "12:00:00",
    "breakEnd": "13:00:00",
    "status": "scheduled"
  },
  {
    "id": 3,
    "employeeId": "emp-001",
    "date": "2025-05-05",
    "startTime": "08:00:00",
    "endTime": "17:00:00",
    "breakStart": "12:00:00",
    "breakEnd": "13:00:00",
    "status": "scheduled"
  },
  {
    "id": 4,
    "employeeId": "emp-001",
    "date": "2025-05-06",
    "startTime": "08:00:00",
    "endTime": "17:00:00",
    "breakStart": "12:00:00",
    "breakEnd": "13:00:00",
    "status": "scheduled"
  },
  {
    "id": 5,
    "employeeId": "emp-001",
    "date": "2025-05-07",
    "startTime": "08:00:00",
    "endTime": "17:00:00",
    "breakStart": "12:00:00",
    "breakEnd": "13:00:00",
    "status": "scheduled"
  },
  {
    "id": 6,
    "employeeId": "emp-001",
    "date": "2025-05-08",
    "startTime": "08:00:00",
    "endTime": "17:00:00",
    "breakStart": "12:00:00",
    "breakEnd": "13:00:00",
    "status": "scheduled"
  },
  {
    "id": 7,
    "employeeId": "emp-001",
    "date": "2025-05-09",
    "startTime": "08:00:00",
    "endTime": "17:00:00",
    "breakStart": "12:00:00",
    "breakEnd": "13:00:00",
    "status": "scheduled"
  },
  {
    "id": 8,
    "employeeId": "E002",
    "date": "2025-05-01",
    "startTime": "09:00:00",
    "endTime": "18:00:00",
    "breakStart": "12:30:00",
    "breakEnd": "13:30:00",
    "status": "scheduled"
  },
  {
    "id": 9,
    "employeeId": "E002",
    "date": "2025-05-02",
    "startTime": "09:00:00",
    "endTime": "18:00:00",
    "breakStart": "12:30:00",
    "breakEnd": "13:30:00",
    "status": "scheduled"
  },
  {
    "id": 10,
    "employeeId": "E002",
    "date": "2025-05-05",
    "startTime": "09:00:00",
    "endTime": "18:00:00",
    "breakStart": "12:30:00",
    "breakEnd": "13:30:00",
    "status": "scheduled"
  },
  {
    "id": 11,
    "employeeId": "E002",
    "date": "2025-05-06",
    "startTime": "09:00:00",
    "endTime": "18:00:00",
    "breakStart": "12:30:00",
    "breakEnd": "13:30:00",
    "status": "scheduled"
  },
  {
    "id": 12,
    "employeeId": "E002",
    "date": "2025-05-07",
    "startTime": "09:00:00",
    "endTime": "18:00:00",
    "breakStart": "12:30:00",
    "breakEnd": "13:30:00",
    "status": "scheduled"
  },
  {
    "id": 13,
    "employeeId": "E002",
    "date": "2025-05-08",
    "startTime": "09:00:00",
    "endTime": "18:00:00",
    "breakStart": "12:30:00",
    "breakEnd": "13:30:00",
    "status": "scheduled"
  },
  {
    "id": 14,
    "employeeId": "E002",
    "date": "2025-05-09",
    "startTime": "09:00:00",
    "endTime": "18:00:00",
    "breakStart": "12:30:00",
    "breakEnd": "13:30:00",
    "status": "scheduled"
  },
  {
    "id": 15,
    "employeeId": "E003",
    "date": "2025-05-01",
    "startTime": "08:30:00",
    "endTime": "17:30:00",
    "breakStart": "12:00:00",
    "breakEnd": "13:00:00",
    "status": "scheduled"
  },
  {
    "id": 16,
    "employeeId": "E003",
    "date": "2025-05-02", 
    "startTime": "08:30:00",
    "endTime": "17:30:00",
    "breakStart": "12:00:00",
    "breakEnd": "13:00:00",
    "status": "scheduled"
  },
  {
    "id": 17,
    "employeeId": "E003",
    "date": "2025-05-05",
    "startTime": "08:30:00",
    "endTime": "17:30:00",
    "breakStart": "12:00:00",
    "breakEnd": "13:00:00",
    "status": "scheduled"
  },
  {
    "id": 18,
    "employeeId": "E003",
    "date": "2025-05-06",
    "startTime": "08:30:00",
    "endTime": "17:30:00",
    "breakStart": "12:00:00",
    "breakEnd": "13:00:00",
    "status": "scheduled"
  },
  {
    "id": 19,
    "employeeId": "E003",
    "date": "2025-05-07",
    "startTime": "08:30:00",
    "endTime": "17:30:00",
    "breakStart": "12:00:00",
    "breakEnd": "13:00:00",
    "status": "scheduled"
  },
  {
    "id": 20,
    "employeeId": "E003",
    "date": "2025-05-08",
    "startTime": "08:30:00",
    "endTime": "17:30:00",
    "breakStart": "12:00:00",
    "breakEnd": "13:00:00",
    "status": "scheduled"
  },
  {
    "id": 21,
    "employeeId": "E003",
    "date": "2025-05-09",
    "startTime": "08:30:00",
    "endTime": "17:30:00",
    "breakStart": "12:00:00",
    "breakEnd": "13:00:00",
    "status": "scheduled"
  },
  {
    "id": 22,
    "employeeId": "E004",
    "date": "2025-05-01",
    "startTime": "07:00:00",
    "endTime": "16:00:00",
    "breakStart": "11:30:00",
    "breakEnd": "12:30:00",
    "status": "scheduled"
  },
  {
    "id": 23,
    "employeeId": "E004",
    "date": "2025-05-02",
    "startTime": "07:00:00",
    "endTime": "16:00:00",
    "breakStart": "11:30:00",
    "breakEnd": "12:30:00",
    "status": "scheduled"
  },
  {
    "id": 24,
    "employeeId": "E004",
    "date": "2025-05-05",
    "startTime": "07:00:00",
    "endTime": "16:00:00",
    "breakStart": "11:30:00",
    "breakEnd": "12:30:00",
    "status": "scheduled"
  },
  {
    "id": 25,
    "employeeId": "E004",
    "date": "2025-05-06",
    "startTime": "07:00:00",
    "endTime": "16:00:00",
    "breakStart": "11:30:00",
    "breakEnd": "12:30:00",
    "status": "scheduled"
  },
  {
    "id": 26,
    "employeeId": "E004",
    "date": "2025-05-07",
    "startTime": "07:00:00",
    "endTime": "16:00:00",
    "breakStart": "11:30:00",
    "breakEnd": "12:30:00",
    "status": "scheduled"
  },
  {
    "id": 27,
    "employeeId": "E004",
    "date": "2025-05-08",
    "startTime": "07:00:00",
    "endTime": "16:00:00",
    "breakStart": "11:30:00",
    "breakEnd": "12:30:00",
    "status": "scheduled"
  },
  {
    "id": 28,
    "employeeId": "E004",
    "date": "2025-05-09",
    "startTime": "07:00:00",
    "endTime": "16:00:00",
    "breakStart": "11:30:00",
    "breakEnd": "12:30:00",
    "status": "scheduled"
  },
  {
    "id": 29,
    "employeeId": "E005",
    "date": "2025-05-01",
    "startTime": "08:00:00",
    "endTime": "17:00:00",
    "breakStart": "12:00:00",
    "breakEnd": "13:00:00",
    "status": "scheduled"
  },
  {
    "id": 30,
    "employeeId": "E005",
    "date": "2025-05-02",
    "startTime": "08:00:00",
    "endTime": "17:00:00",
    "breakStart": "12:00:00",
    "breakEnd": "13:00:00",
    "status": "scheduled"
  },
  {
    "id": 31,
    "employeeId": "E005",
    "date": "2025-05-05",
    "startTime": "08:00:00",
    "endTime": "17:00:00",
    "breakStart": "12:00:00",
    "breakEnd": "13:00:00",
    "status": "scheduled"
  },
  {
    "id": 32,
    "employeeId": "E005",
    "date": "2025-05-06",
    "startTime": "08:00:00",
    "endTime": "17:00:00",
    "breakStart": "12:00:00",
    "breakEnd": "13:00:00",
    "status": "scheduled"
  },
  {
    "id": 33,
    "employeeId": "E005",
    "date": "2025-05-07",
    "startTime": "08:00:00",
    "endTime": "17:00:00",
    "breakStart": "12:00:00",
    "breakEnd": "13:00:00",
    "status": "scheduled"
  },
  {
    "id": 34,
    "employeeId": "E005",
    "date": "2025-05-08",
    "startTime": "08:00:00",
    "endTime": "17:00:00",
    "breakStart": "12:00:00",
    "breakEnd": "13:00:00",
    "status": "scheduled"
  },
  {
    "id": 35,
    "employeeId": "E005",
    "date": "2025-05-09",
    "startTime": "08:00:00",
    "endTime": "17:00:00",
    "breakStart": "12:00:00",
    "breakEnd": "13:00:00",
    "status": "scheduled"
  }
]
